nested2nested/README.MD
nested2nested/__init__.py
nested2nested/requirements.txt
nested2nested/thirdparty.json
nested2nested-0.10.dist-info/LICENSE.rst
nested2nested-0.10.dist-info/METADATA
nested2nested-0.10.dist-info/WHEEL
nested2nested-0.10.dist-info/top_level.txt
nested2nested-0.10.dist-info/RECORD
