Metadata-Version: 2.1
Name: nested2nested
Version: 0.10
Summary: converts a nested list into a nested dictionary with support for multi-level keys and preserving the order
Home-page: https://github.com/hansalemaos/nested2nested
Author: Johannes Fischer
Author-email: aulasparticularesdealemaosp@gmail.com
License: MIT
Keywords: nested iterables,dict
Classifier: Development Status :: 4 - Beta
Classifier: Programming Language :: Python :: 3 :: Only
Classifier: Programming Language :: Python :: 3.10
Classifier: Topic :: Software Development :: Libraries :: Python Modules
Classifier: Topic :: Utilities
License-File: LICENSE.rst
